treecrawl/__init__.py
treecrawl/casehelper.py
treecrawl/transformer.py
treecrawl/utility.py
treecrawl-0.1.24.dist-info/AUTHORS.rst
treecrawl-0.1.24.dist-info/LICENSE
treecrawl-0.1.24.dist-info/METADATA
treecrawl-0.1.24.dist-info/WHEEL
treecrawl-0.1.24.dist-info/top_level.txt
treecrawl-0.1.24.dist-info/RECORD
