Metadata-Version: 2.1
Name: treecrawl
Version: 0.1.24
Summary: libraries to make it easier to maniuplate files in a directory tree
Home-page: https://github.com/natemarks/treecrawl
Author: Nate Marks
Author-email: npmarks@gmail.com
License: MIT license
Keywords: treecrawl
Platform: UNKNOWN
Classifier: Development Status :: 2 - Pre-Alpha
Classifier: Intended Audience :: Developers
Classifier: License :: OSI Approved :: MIT License
Classifier: Natural Language :: English
Classifier: Programming Language :: Python :: 3
Classifier: Programming Language :: Python :: 3.6
Classifier: Programming Language :: Python :: 3.7
Classifier: Programming Language :: Python :: 3.8
Requires-Python: >=3.6
Provides-Extra: dev
Requires-Dist: pip (==20.2.2) ; extra == 'dev'
Requires-Dist: setuptools (==49.2.0) ; extra == 'dev'
Requires-Dist: black (==19.10b0) ; extra == 'dev'
Requires-Dist: bump2version ; extra == 'dev'
Requires-Dist: docutils (==0.16) ; extra == 'dev'
Requires-Dist: flake8 (==3.8.3) ; extra == 'dev'
Requires-Dist: nox (==2020.5.24) ; extra == 'dev'
Requires-Dist: pytest (==5.4.3) ; extra == 'dev'
Requires-Dist: Sphinx (==3.1.2) ; extra == 'dev'
Requires-Dist: twine (==3.2.0) ; extra == 'dev'
Requires-Dist: wheel (==0.34.2) ; extra == 'dev'
Requires-Dist: check-manifest (==0.42) ; extra == 'dev'
